FIS_extension/__init__.py
FIS_extension/_version.py
fis_extension-0.1.0.data/data/share/jupyter/labextensions/FIS_extension/build_log.json
fis_extension-0.1.0.data/data/share/jupyter/labextensions/FIS_extension/package.json
fis_extension-0.1.0.data/data/share/jupyter/labextensions/FIS_extension/static/lib_index_js.c1b9e2d8410195807bff.js
fis_extension-0.1.0.data/data/share/jupyter/labextensions/FIS_extension/static/lib_index_js.c1b9e2d8410195807bff.js.map
fis_extension-0.1.0.data/data/share/jupyter/labextensions/FIS_extension/static/remoteEntry.c2719c4cf4d8d15acfa3.js
fis_extension-0.1.0.data/data/share/jupyter/labextensions/FIS_extension/static/remoteEntry.c2719c4cf4d8d15acfa3.js.map
fis_extension-0.1.0.data/data/share/jupyter/labextensions/FIS_extension/static/style.js
fis_extension-0.1.0.data/data/share/jupyter/labextensions/FIS_extension/static/style_index_js.7e5d64c264b2f949a2a2.js
fis_extension-0.1.0.data/data/share/jupyter/labextensions/FIS_extension/static/style_index_js.7e5d64c264b2f949a2a2.js.map
fis_extension-0.1.0.data/data/share/jupyter/labextensions/FIS_extension/install.json
fis_extension-0.1.0.dist-info/METADATA
fis_extension-0.1.0.dist-info/WHEEL
fis_extension-0.1.0.dist-info/licenses/LICENSE
fis_extension-0.1.0.dist-info/RECORD
